Metadata-Version: 2.1
Name: manopot
Version: 1.0.0
Summary: Simple TCP HoneyPot
Home-page: UNKNOWN
Author: Apurv Goyal
Author-email: apurv.goyal01@gmail.com
License: MIT
Platform: UNKNOWN
